multigaussampler/MGSampler.py
multigaussampler/__init__.py
multigaussampler-0.1.1.dist-info/METADATA
multigaussampler-0.1.1.dist-info/WHEEL
multigaussampler-0.1.1.dist-info/top_level.txt
multigaussampler-0.1.1.dist-info/RECORD
